Metadata-Version: 1.1
Name: pyicu-praxa
Version: 1.7
Summary: Python extension wrapping the ICU C++ API (Praxa fork)
Home-page: http://pyicu.osafoundation.org/
Author: Alexander Bohn
Author-email: fish2000@gmail.com
License: UNKNOWN
Platform: UNKNOWN
Classifier: Development Status :: 5 - Production/Stable
Classifier: Environment :: Console
Classifier: Intended Audience :: Developers
Classifier: License :: OSI Approved
Classifier: Operating System :: OS Independent
Classifier: Programming Language :: C++
Classifier: Programming Language :: Python
Classifier: Programming Language :: Python :: 2
Classifier: Programming Language :: Python :: 3
Classifier: Topic :: Software Development :: Localization
Classifier: Topic :: Software Development :: Internationalization
